LICENSE.txt
MANIFEST.in
README.md
requirements.txt
setup.py
pyaxiom/__init__.py
pyaxiom/urn.py
pyaxiom/utils.py
pyaxiom.egg-info/PKG-INFO
pyaxiom.egg-info/SOURCES.txt
pyaxiom.egg-info/dependency_links.txt
pyaxiom.egg-info/entry_points.txt
pyaxiom.egg-info/requires.txt
pyaxiom.egg-info/top_level.txt
pyaxiom/netcdf/__init__.py
pyaxiom/netcdf/cf.py
pyaxiom/netcdf/clone.py
pyaxiom/netcdf/dataset.py
pyaxiom/netcdf/utils.py
pyaxiom/netcdf/grids/__init__.py
pyaxiom/netcdf/grids/binner.py
pyaxiom/netcdf/grids/collection.py
pyaxiom/netcdf/sensors/__init__.py
pyaxiom/netcdf/sensors/profile.py
pyaxiom/netcdf/sensors/timeseries.py
pyaxiom/netcdf/sensors/dsg/__init__.py
pyaxiom/netcdf/sensors/dsg/profile/__init__.py
pyaxiom/netcdf/sensors/dsg/profile/im.py
pyaxiom/netcdf/sensors/dsg/profile/om.py
pyaxiom/netcdf/sensors/dsg/trajectory/__init__.py
pyaxiom/netcdf/sensors/dsg/trajectory/cr.py
pyaxiom/netcdf/sensors/dsg/trajectory/im.py
pyaxiom/netcdf/sensors/dsg/trajectory/ir.py
pyaxiom/netcdf/sensors/dsg/trajectoryProfile/__init__.py
pyaxiom/netcdf/sensors/dsg/trajectoryProfile/cr.py
pyaxiom/tests/__init__.py
pyaxiom/tests/test_enhanced_dataset.py
pyaxiom/tests/test_netcdf_collection.py
pyaxiom/tests/test_timeseries.py
pyaxiom/tests/test_urn.py
pyaxiom/tests/test_utils.py